hotspots/__init__.py
hotspots/atomic_hotspot_calculation.py
hotspots/calculation.py
hotspots/data.py
hotspots/excluded_het_id.txt
hotspots/grid_extension.py
hotspots/hs_docking.py
hotspots/hs_io.py
hotspots/hs_pharmacophore.py
hotspots/hs_utilities.py
hotspots/pdb_python_api.py
hotspots/protoss.py
hotspots/result.py
hotspots/siena.py
hotspots/template_strings.py
hotspots/probes/rotate-acceptor_3_3d.mol2
hotspots/probes/rotate-acceptor_3_flat.mol2
hotspots/probes/rotate-acceptor_4_3d.mol2
hotspots/probes/rotate-acceptor_4_flat.mol2
hotspots/probes/rotate-acceptor_5_3d.mol2
hotspots/probes/rotate-acceptor_5_flat.mol2
hotspots/probes/rotate-acceptor_6_3d.mol2
hotspots/probes/rotate-acceptor_6_flat.mol2
hotspots/probes/rotate-acceptor_7_3d.mol2
hotspots/probes/rotate-acceptor_7_flat.mol2
hotspots/probes/rotate-acceptor_8_3d.mol2
hotspots/probes/rotate-acceptor_8_flat.mol2
hotspots/probes/rotate-apolar_3_3d.mol2
hotspots/probes/rotate-apolar_3_flat.mol2
hotspots/probes/rotate-apolar_4_3d.mol2
hotspots/probes/rotate-apolar_4_flat.mol2
hotspots/probes/rotate-apolar_5_3d.mol2
hotspots/probes/rotate-apolar_5_flat.mol2
hotspots/probes/rotate-apolar_6_3d.mol2
hotspots/probes/rotate-apolar_6_flat.mol2
hotspots/probes/rotate-apolar_7_3d.mol2
hotspots/probes/rotate-apolar_7_flat.mol2
hotspots/probes/rotate-apolar_8_3d.mol2
hotspots/probes/rotate-apolar_8_flat.mol2
hotspots/probes/rotate-donor_3_3d.mol2
hotspots/probes/rotate-donor_3_flat.mol2
hotspots/probes/rotate-donor_4_3d.mol2
hotspots/probes/rotate-donor_4_flat.mol2
hotspots/probes/rotate-donor_5_3d.mol2
hotspots/probes/rotate-donor_5_flat.mol2
hotspots/probes/rotate-donor_6_3d.mol2
hotspots/probes/rotate-donor_6_flat.mol2
hotspots/probes/rotate-donor_7_3d.mol2
hotspots/probes/rotate-donor_7_flat.mol2
hotspots/probes/rotate-donor_8_3d.mol2
hotspots/probes/rotate-donor_8_flat.mol2
hotspots/probes/rotate-negative_3_flat.mol2
hotspots/probes/rotate-negative_7_flat.mol2
hotspots/probes/rotate-negative_8_flat.mol2
hotspots-1.0.3.dist-info/LICENSE
hotspots-1.0.3.dist-info/METADATA
hotspots-1.0.3.dist-info/WHEEL
hotspots-1.0.3.dist-info/top_level.txt
hotspots-1.0.3.dist-info/RECORD
