Metadata-Version: 2.1
Name: hotspots
Version: 1.0.3
Summary: UNKNOWN
Home-page: https://github.com/prcurran/hotspots
Author: Chris Radoux, Peter Curran, Mihaela Smilova
Author-email: pcurran@ccdc.cam.ac.uk
License: MIT
Platform: UNKNOWN
Requires-Dist: numpy
Requires-Dist: csd-python-api (>=2.0.0)
Requires-Dist: matplotlib (==2.2.3)
Requires-Dist: scipy
Requires-Dist: sklearn
Requires-Dist: scikit-image
Requires-Dist: hdbscan
Requires-Dist: pandas
Requires-Dist: futures
Requires-Dist: tqdm (==4.31.1)
Requires-Dist: xmltodict (==0.12.0)
